README.md
setup.py
wiserSmartAPI/__init__.py
wiserSmartAPI/wiserSmart.py
wiser_smart_api.egg-info/PKG-INFO
wiser_smart_api.egg-info/SOURCES.txt
wiser_smart_api.egg-info/dependency_links.txt
wiser_smart_api.egg-info/top_level.txt