Metadata-Version: 2.1
Name: wiser-smart-api
Version: 1.0.6
Summary: A simple API for accessing data on the Schneider Wiser Smart system (The white cross)
Home-page: https://github.com/tomtomfx/wiser-smart-api
Author: Thomas Fayoux
Author-email: thomas.fayoux@gmail.com
License: MIT
Platform: UNKNOWN
Classifier: Programming Language :: Python :: 3
Classifier: License :: OSI Approved :: MIT License
Classifier: Operating System :: OS Independent
